pytest_fastest/__init__.py
pytest_fastest/git.py
pytest_fastest-0.0.12.dist-info/LICENSE
pytest_fastest-0.0.12.dist-info/METADATA
pytest_fastest-0.0.12.dist-info/WHEEL
pytest_fastest-0.0.12.dist-info/entry_points.txt
pytest_fastest-0.0.12.dist-info/RECORD
