Metadata-Version: 2.1
Name: pytest-fastest
Version: 0.0.12
Summary: Use SCM and coverage to run only needed tests
Home-page: https://github.com/kstrauser/pytest-fastest
License: MIT
Author: Kirk Strauser
Author-email: kirk@amino.com
Requires-Python: >=3.8
Classifier: Development Status :: 4 - Beta
Classifier: Framework :: Pytest
Classifier: Intended Audience :: Developers
Classifier: License :: OSI Approved :: MIT License
Classifier: Operating System :: OS Independent
Classifier: Programming Language :: Python :: 3
Classifier: Programming Language :: Python :: 3.8
Classifier: Programming Language :: Python :: 3.9
Classifier: Programming Language :: Python :: 3.10
Classifier: Programming Language :: Python :: 3.11
Classifier: Topic :: Software Development :: Testing
Requires-Dist: pytest (>=4.4)
Project-URL: Documentation, http://pytest-fastest.readthedocs.io/en/latest/
Project-URL: Repository, https://github.com/kstrauser/pytest-fastest
